{
    "version": 2,
    "settings": {
        "color": {
            "defaultPalette": false,
            "palette": [
                {
                    "name": "Primary",
                    "slug": "primary",
                    "color": "#f15320"
                },
                {
                    "name": "Secondary",
                    "slug": "secondary",
                    "color": "#a7c9e7"
                },
                {
                    "name": "Light Grey",
                    "slug": "lightgrey",
                    "color": "#D1D1D1"
                },
                {
                    "name": "Dark Grey",
                    "slug": "darkgrey",
                    "color": "#575757"
                }
            ]
        }
    }
}